idspy_dictionaries/__init__.py
idspy_dictionaries/_version.py
idspy_dictionaries/dataclasses_idsschema.py
idspy_dictionaries/header.py
idspy_dictionaries/setup.py
idspy_dictionaries/ids_amns_data/__init__.py
idspy_dictionaries/ids_amns_data/amns_data.py
idspy_dictionaries/ids_b_field_non_axisymmetric/__init__.py
idspy_dictionaries/ids_b_field_non_axisymmetric/b_field_non_axisymmetric.py
idspy_dictionaries/ids_barometry/__init__.py
idspy_dictionaries/ids_barometry/barometry.py
idspy_dictionaries/ids_bolometer/__init__.py
idspy_dictionaries/ids_bolometer/bolometer.py
idspy_dictionaries/ids_bremsstrahlung_visible/__init__.py
idspy_dictionaries/ids_bremsstrahlung_visible/bremsstrahlung_visible.py
idspy_dictionaries/ids_calorimetry/__init__.py
idspy_dictionaries/ids_calorimetry/calorimetry.py
idspy_dictionaries/ids_camera_ir/__init__.py
idspy_dictionaries/ids_camera_ir/camera_ir.py
idspy_dictionaries/ids_camera_visible/__init__.py
idspy_dictionaries/ids_camera_visible/camera_visible.py
idspy_dictionaries/ids_camera_x_rays/__init__.py
idspy_dictionaries/ids_camera_x_rays/camera_x_rays.py
idspy_dictionaries/ids_charge_exchange/__init__.py
idspy_dictionaries/ids_charge_exchange/charge_exchange.py
idspy_dictionaries/ids_coils_non_axisymmetric/__init__.py
idspy_dictionaries/ids_coils_non_axisymmetric/coils_non_axisymmetric.py
idspy_dictionaries/ids_controllers/__init__.py
idspy_dictionaries/ids_controllers/controllers.py
idspy_dictionaries/ids_core_instant_changes/__init__.py
idspy_dictionaries/ids_core_instant_changes/core_instant_changes.py
idspy_dictionaries/ids_core_profiles/__init__.py
idspy_dictionaries/ids_core_profiles/core_profiles.py
idspy_dictionaries/ids_core_sources/__init__.py
idspy_dictionaries/ids_core_sources/core_sources.py
idspy_dictionaries/ids_core_transport/__init__.py
idspy_dictionaries/ids_core_transport/core_transport.py
idspy_dictionaries/ids_cryostat/__init__.py
idspy_dictionaries/ids_cryostat/cryostat.py
idspy_dictionaries-40001.5.1.dist-info/licenses/LICENSE
idspy_dictionaries-40001.5.1.dist-info/METADATA
idspy_dictionaries-40001.5.1.dist-info/WHEEL
idspy_dictionaries-40001.5.1.dist-info/top_level.txt
idspy_dictionaries-40001.5.1.dist-info/RECORD
