Metadata-Version: 2.4
Name: idspy_dictionaries
Version: 40001.5.1
Summary: IMAS Data Dictionaries converted to Python Dataclass used in the IMAS-GK/IDSPy parser
Author-email: Guillaume Fuhr <guillaume.fuhr@univ-amu.fr>
Project-URL: Homepage, https://gitlab.com/gkdb/idspy_dictionaries
Project-URL: Bug Tracker, https://gitlab.com/gkdb/idspy_dictionaries/-/issues
Classifier: Development Status :: 5 - Production/Stable
Classifier: Environment :: Console
Classifier: Intended Audience :: Science/Research
Classifier: Operating System :: OS Independent
Classifier: Programming Language :: Python :: 3 :: Only
Classifier: Programming Language :: Python :: 3.9
Classifier: Programming Language :: Python :: 3.10
Classifier: Programming Language :: Python :: 3.11
Classifier: Topic :: Scientific/Engineering
Requires-Python: >=3.9
License-File: LICENSE
Dynamic: license-file
